spikewrap/__init__.py
spikewrap/configs/config_utils.py
spikewrap/configs/hpc.py
spikewrap/configs/_backend/canon.py
spikewrap/configs/_backend/_default_configs/neuropixels+kilosort2_5.yaml
spikewrap/configs/_backend/_default_configs/neuropixels+mountainsort5.yaml
spikewrap/examples/example_session.py
spikewrap/examples/example_tiny_data/openephys/README.md
spikewrap/examples/example_tiny_data/openephys/rawdata/sub-001/ses-001/ephys/Record Node 104/settings.xml
spikewrap/examples/example_tiny_data/openephys/rawdata/sub-001/ses-001/ephys/Record Node 104/experiment1/recording1/structure.oebin
spikewrap/examples/example_tiny_data/openephys/rawdata/sub-001/ses-001/ephys/Record Node 104/experiment1/recording1/sync_messages.txt
spikewrap/examples/example_tiny_data/openephys/rawdata/sub-001/ses-001/ephys/Record Node 104/experiment1/recording1/continuous/Neuropix-PXI-100.ProbeA-AP/continuous.dat
spikewrap/examples/example_tiny_data/openephys/rawdata/sub-001/ses-001/ephys/Record Node 104/experiment1/recording1/continuous/Neuropix-PXI-100.ProbeA-AP/sample_numbers.npy
spikewrap/examples/example_tiny_data/openephys/rawdata/sub-001/ses-001/ephys/Record Node 104/experiment1/recording1/continuous/Neuropix-PXI-100.ProbeA-AP/timestamps.npy
spikewrap/examples/example_tiny_data/openephys/rawdata/sub-001/ses-001/ephys/Record Node 104/experiment1/recording1/events/MessageCenter/sample_numbers.npy
spikewrap/examples/example_tiny_data/openephys/rawdata/sub-001/ses-001/ephys/Record Node 104/experiment1/recording1/events/MessageCenter/text.npy
spikewrap/examples/example_tiny_data/openephys/rawdata/sub-001/ses-001/ephys/Record Node 104/experiment1/recording1/events/MessageCenter/timestamps.npy
spikewrap/examples/example_tiny_data/openephys/rawdata/sub-001/ses-001/ephys/Record Node 104/experiment1/recording1/events/Neuropix-PXI-100.ProbeA-AP/TTL/full_words.npy
spikewrap-0.3.1.dist-info/licenses/LICENSE
spikewrap-0.3.1.dist-info/METADATA
spikewrap-0.3.1.dist-info/WHEEL
spikewrap-0.3.1.dist-info/top_level.txt
spikewrap-0.3.1.dist-info/RECORD
