Metadata-Version: 2.4
Name: spikewrap
Version: 0.3.1
Summary: Run extracellular electrophysiology analysis with SpikeInterface
Author-email: Joe Ziminski <joseph.j.ziminski@gmail.com>
License: BSD-3-Clause
Project-URL: homepage, https://github.com/JoeZiminski/spikewrap
Project-URL: bug_tracker, https://github.com/JoeZiminski/spikewrap/issues
Project-URL: documentation, https://github.com/JoeZiminski/spikewrap
Project-URL: source_code, https://github.com/JoeZiminski/spikewrap
Project-URL: user_support, https://github.com/JoeZiminski/spikewrap/issues
Classifier: Development Status :: 2 - Pre-Alpha
Classifier: Programming Language :: Python
Classifier: Programming Language :: Python :: 3
Classifier: Programming Language :: Python :: 3.9
Classifier: Programming Language :: Python :: 3.10
Classifier: Programming Language :: Python :: 3.11
Classifier: Programming Language :: Python :: 3.12
Classifier: Operating System :: OS Independent
Classifier: License :: OSI Approved :: BSD License
Requires-Python: <3.13,>=3.9.0
License-File: LICENSE
Requires-Dist: spikeinterface[full]==0.102.3
Requires-Dist: neo==0.14.1
Requires-Dist: submitit
Requires-Dist: slurmio
Requires-Dist: psutil
Requires-Dist: toml
Requires-Dist: PyYAML
Provides-Extra: dev
Requires-Dist: pytest; extra == "dev"
Requires-Dist: pytest-cov; extra == "dev"
Requires-Dist: coverage; extra == "dev"
Requires-Dist: tox; extra == "dev"
Requires-Dist: black; extra == "dev"
Requires-Dist: mypy; extra == "dev"
Requires-Dist: pre-commit; extra == "dev"
Requires-Dist: ruff; extra == "dev"
Requires-Dist: setuptools_scm; extra == "dev"
Requires-Dist: types-setuptools; extra == "dev"
Requires-Dist: types-PyYAML; extra == "dev"
Requires-Dist: types-toml; extra == "dev"
Requires-Dist: mountainsort5; sys_platform != "darwin" and extra == "dev"
Dynamic: license-file
